nowcl/__init__.py
nowcl-0.1.0.dist-info/METADATA
nowcl-0.1.0.dist-info/WHEEL
nowcl-0.1.0.dist-info/RECORD
