Metadata-Version: 2.1
Name: nowcl
Version: 0.1.0
Summary: now
Author: N
Requires-Python: >=3.11,<4.0
Classifier: Programming Language :: Python :: 3
Classifier: Programming Language :: Python :: 3.11
